setup.py
ana_py/Binomialdistribution.py
ana_py/Gaussiandistribution.py
ana_py/Generaldistribution.py
ana_py/__init__.py
ana_py.egg-info/PKG-INFO
ana_py.egg-info/SOURCES.txt
ana_py.egg-info/dependency_links.txt
ana_py.egg-info/not-zip-safe
ana_py.egg-info/top_level.txt