Metadata-Version: 1.0
Name: ana-py
Version: 0.1
Summary: Python package for Gaussian and Binomial Distribution
Home-page: UNKNOWN
Author: Shaswat Rajput
Author-email: shaswatrajput@outlook.com
License: UNKNOWN
Platform: UNKNOWN
